wintry/__init__.py
wintry/cli/__init__.py
wintry/cli/cli.py
wintry/cli/commands/__init__.py
wintry/cli/commands/generate.py
wintry/cli/commands/new.py
wintry/cli/templates/__init__.py
wintry/cli/templates/generate/__init__.py
wintry/cli/templates/generate/controller.py.jinja2
wintry/cli/templates/generate/model.py.j2
wintry/cli/templates/project/cookiecutter.json
wintry/cli/templates/project/{{cookiecutter.project_name}}/.gitignore
wintry/cli/templates/project/{{cookiecutter.project_name}}/__init__.py
wintry/cli/templates/project/{{cookiecutter.project_name}}/apps/__init__.py
wintry/cli/templates/project/{{cookiecutter.project_name}}/apps/contrib/__init__.py
wintry/cli/templates/project/{{cookiecutter.project_name}}/apps/contrib/dependencies.py
wintry/cli/templates/project/{{cookiecutter.project_name}}/apps/contrib/services.py
wintry/cli/templates/project/{{cookiecutter.project_name}}/apps/{{cookiecutter.project_name}}/__init__.py
wintry/cli/templates/project/{{cookiecutter.project_name}}/apps/{{cookiecutter.project_name}}/entrypoints/__init__.py
wintry/cli/templates/project/{{cookiecutter.project_name}}/apps/{{cookiecutter.project_name}}/inputs/__init__.py
wintry/cli/templates/project/{{cookiecutter.project_name}}/apps/{{cookiecutter.project_name}}/inputs/commands.py
wintry/cli/templates/project/{{cookiecutter.project_name}}/apps/{{cookiecutter.project_name}}/inputs/events.py
wintry/cli/templates/project/{{cookiecutter.project_name}}/apps/{{cookiecutter.project_name}}/models/__init__.py
wintry/cli/templates/project/{{cookiecutter.project_name}}/apps/{{cookiecutter.project_name}}/repositories/__init__.py
wintry/cli/templates/project/{{cookiecutter.project_name}}/apps/{{cookiecutter.project_name}}/services/__init__.py
wintry/cli/templates/project/{{cookiecutter.project_name}}/apps/{{cookiecutter.project_name}}/views/__init__.py
wintry/cli/templates/project/{{cookiecutter.project_name}}/apps/{{cookiecutter.project_name}}/views/viewmodels.py
wintry-1.0.0.dist-info/entry_points.txt
wintry-1.0.0.dist-info/LICENSE
wintry-1.0.0.dist-info/WHEEL
wintry-1.0.0.dist-info/METADATA
wintry-1.0.0.dist-info/RECORD
