Metadata-Version: 2.1
Name: wintry
Version: 1.0.0
Summary: Fastapi with steroids
Home-page: https://adriangs1996.github.io/wintry
License: MIT
Keywords: web-framework,api-rest,wintry,fastapi
Author: adriangs1996
Author-email: adriangonzalezsanchez1996@gmail.com
Requires-Python: >=3.10,<4.0
Classifier: License :: OSI Approved :: MIT License
Classifier: Programming Language :: Python :: 3
Classifier: Programming Language :: Python :: 3.10
Requires-Dist: cookiecutter (>=1.7.3,<2.0.0)
Requires-Dist: fastapi (>=0.78.0,<0.79.0)
Requires-Dist: redis (>=4.3.4,<5.0.0)
Requires-Dist: typer[all] (>=0.4.1,<0.5.0)
Requires-Dist: uvicorn[standard] (>=0.17.6,<0.18.0)
Requires-Dist: wrapt (>=1.14.1,<2.0.0)
Project-URL: Repository, https://github.com/adriangs1996/wintry
